landauer/__init__.py
landauer/evaluate.py
landauer/graph.py
landauer/naive.py
landauer/parse.py
landauer/simulate.py
landauer-0.0.1.dist-info/LICENSE
landauer-0.0.1.dist-info/METADATA
landauer-0.0.1.dist-info/WHEEL
landauer-0.0.1.dist-info/top_level.txt
landauer-0.0.1.dist-info/RECORD
