Metadata-Version: 2.1
Name: landauer
Version: 0.0.1
Summary: Python toolkit to support fundamental energy limits and reversible computing research
Author-email: Marco Diniz Sousa <mtdsousa@gmail.com>
License: MIT License        
Project-URL: Homepage, https://github.com/mtdsousa/landauer
Project-URL: Bug Tracker, https://github.com/mtdsousa/landauer/issues
Classifier: Programming Language :: Python :: 3
Classifier: License :: OSI Approved :: MIT License
Classifier: Operating System :: OS Independent
Requires-Python: >=3.10
License-File: LICENSE
Requires-Dist: antlr4-verilog (==4.0.0)
Requires-Dist: graphviz (~=0.19.1)
Requires-Dist: matplotlib (~=3.5.1)
Requires-Dist: networkx (~=2.6.3)
Requires-Dist: pydot (~=1.4.2)
Requires-Dist: seaborn (~=0.11.2)
Requires-Dist: tqdm (~=4.64.0)
